ezlink/__init__.py
ezlink/__main__.py
ezlink/backoff.py
ezlink/enums.py
ezlink/exceptions.py
ezlink/filters.py
ezlink/lfu.py
ezlink/node.py
ezlink/payloads.py
ezlink/player.py
ezlink/py.typed
ezlink/queue.py
ezlink/tracks.py
ezlink/utils.py
ezlink/websocket.py
ezlink/types/__init__.py
ezlink/types/filters.py
ezlink/types/request.py
ezlink/types/response.py
ezlink/types/state.py
ezlink/types/stats.py
ezlink/types/tracks.py
ezlink/types/websocket.py
ezlink-3.3.0.dist-info/LICENSE
ezlink-3.3.0.dist-info/METADATA
ezlink-3.3.0.dist-info/WHEEL
ezlink-3.3.0.dist-info/top_level.txt
ezlink-3.3.0.dist-info/RECORD
