Metadata-Version: 2.1
Name: ezlink
Version: 3.3.0
Summary: A robust and powerful, fully asynchronous Lavalink wrapper built for discord.py in Python.
Author-email: "PythonistaGuild, EvieePy" <evieepy@gmail.com>
Project-URL: Homepage, https://github.com/PythonistaGuild/ezlink
Classifier: License :: OSI Approved :: MIT License
Classifier: Intended Audience :: Developers
Classifier: Natural Language :: English
Classifier: Operating System :: OS Independent
Classifier: Programming Language :: Python :: 3.10
Classifier: Programming Language :: Python :: 3.11
Classifier: Programming Language :: Python :: 3.12
Classifier: Topic :: Internet
Classifier: Topic :: Software Development :: Libraries
Classifier: Topic :: Software Development :: Libraries :: Python Modules
Classifier: Topic :: Utilities
Requires-Python: >=3.10
License-File: LICENSE
Requires-Dist: aiohttp <4,>=3.7.4
Requires-Dist: py-cord
Requires-Dist: yarl >=1.9.2
Requires-Dist: async-timeout
Requires-Dist: typing-extensions
